dasy/README.org
dasy/__init__.py
dasy/builtin/functions.py
dasy/builtin/macros.hy
dasy/compiler.py
dasy/main.py
dasy/parser/__init__.py
dasy/parser/builtins.hy
dasy/parser/comparisons.py
dasy/parser/core.py
dasy/parser/macros.py
dasy/parser/nodes.py
dasy/parser/ops.py
dasy/parser/output.py
dasy/parser/parse.py
dasy/parser/stmt.py
dasy/parser/utils.hy
dasy-0.1.29.dist-info/entry_points.txt
dasy-0.1.29.dist-info/WHEEL
dasy-0.1.29.dist-info/METADATA
dasy-0.1.29.dist-info/RECORD
