Metadata-Version: 2.1
Name: dasy
Version: 0.1.29
Summary: an evm lisp
Author: z80
Author-email: z80@ophy.xyz
Requires-Python: >=3.10,<3.12
Classifier: Programming Language :: Python :: 3
Classifier: Programming Language :: Python :: 3.10
Requires-Dist: argparse (>=1.4.0,<2.0.0)
Requires-Dist: dasy-hy (==0.24.2)
Requires-Dist: eth-abi (>=4.0.0,<5.0.0)
Requires-Dist: eth-typing (>=3.2.0,<4.0.0)
Requires-Dist: hyrule (>=0.2,<0.3)
Requires-Dist: py-evm (>=0.6.1a2)
Requires-Dist: pytest (>=7.1.3,<8.0.0)
Requires-Dist: vyper (>=0.3.10,<0.4.0)
